setup.py
HWFormatter.egg-info/PKG-INFO
HWFormatter.egg-info/SOURCES.txt
HWFormatter.egg-info/dependency_links.txt
HWFormatter.egg-info/requires.txt
HWFormatter.egg-info/top_level.txt
scripts/format_HW
src/HWFormatter/__init__.py
src/HWFormatter/formatter.py