Metadata-Version: 1.0
Name: HWFormatter
Version: 0.4
Summary: Format submitted homework assignments from Blackboard into PDFs
Home-page: http://github.com/dgrtwo/HW-Formatter
Author: David Robinson
Author-email: dgrtwo@princeton.edu
License: UNKNOWN
Platform: UNKNOWN
